MANIFEST.in
README.md
requirements.txt
setup.py
cmd_command/__init__.py
cmd_command/agent_configuration.py
data/init-script/harp-agent
harp_agent/__init__.py
harp_agent/app.py
harp_agent.egg-info/PKG-INFO
harp_agent.egg-info/SOURCES.txt
harp_agent.egg-info/dependency_links.txt
harp_agent.egg-info/entry_points.txt
harp_agent.egg-info/not-zip-safe
harp_agent.egg-info/requires.txt
harp_agent.egg-info/top_level.txt
harp_agent/endpoints/__init__.py
harp_agent/endpoints/notifications.py
harp_agent/logic/__init__.py
harp_agent/logic/config_update.py
harp_agent/logic/prepare_service.py
harp_agent/models/__init__.py
harp_agent/notifications_collectors/__init__.py
harp_agent/notifications_collectors/icinga_collector.py
harp_agent/notifications_collectors/push_notification.py
harp_agent/notifications_collectors/zabbix_collector.py
harp_agent/settings/__init__.py
harp_agent/settings/app_settings.py