Metadata-Version: 1.2
Name: harp-agent
Version: 1.0.2
Summary: Harp Agent
Home-page: UNKNOWN
Author: 
Author-email: 
License: UNKNOWN
Platform: UNKNOWN
Requires-Python: >3.7.0
